simpledspy/__init__.py
simpledspy/cli.py
simpledspy/evaluator.py
simpledspy/logger.py
simpledspy/metrics.py
simpledspy/module_caller.py
simpledspy/module_factory.py
simpledspy/optimization_manager.py
simpledspy/pipeline_manager.py
simpledspy/settings.py
simpledspy-0.3.1.dist-info/LICENSE
simpledspy-0.3.1.dist-info/METADATA
simpledspy-0.3.1.dist-info/WHEEL
simpledspy-0.3.1.dist-info/entry_points.txt
simpledspy-0.3.1.dist-info/RECORD
