Metadata-Version: 2.1
Name: simpledspy
Version: 0.3.1
Summary: A simplified DSPy interface
Home-page: https://github.com/tomdoerr/simpledspy
License: MIT
Keywords: dspy,llm,pipeline,nlp
Author: Tom Dörr
Author-email: tomdoerr96@gmail.com
Requires-Python: >=3.9,<4.0
Classifier: Development Status :: 4 - Beta
Classifier: Intended Audience :: Developers
Classifier: License :: OSI Approved :: MIT License
Classifier: Programming Language :: Python :: 3
Classifier: Programming Language :: Python :: 3.9
Classifier: Programming Language :: Python :: 3.10
Classifier: Programming Language :: Python :: 3.11
Classifier: Programming Language :: Python :: 3.12
Classifier: Programming Language :: Python :: 3.13
Classifier: Topic :: Scientific/Engineering :: Artificial Intelligence
Requires-Dist: dspy (>=2.5.0)
Project-URL: Repository, https://github.com/tomdoerr/simpledspy
